{"count":708,"items":[{"id":19438,"rating":0,"product":9371,"disease":5210},{"id":19437,"rating":0,"product":9371,"disease":5211},{"id":19439,"rating":0,"product":9371,"disease":5213},{"id":19566,"rating":0,"product":9433,"disease":2476},{"id":19542,"rating":0,"product":9433,"disease":5210},{"id":19543,"rating":0,"product":9433,"disease":5211},{"id":19544,"rating":0,"product":9433,"disease":5213},{"id":19565,"rating":0,"product":9433,"disease":5226},{"id":19569,"rating":0,"product":9433,"disease":5229},{"id":19570,"rating":0,"product":9433,"disease":5230},{"id":19571,"rating":0,"product":9433,"disease":5232},{"id":19573,"rating":0,"product":9434,"disease":5225},{"id":19577,"rating":0,"product":9436,"disease":2478},{"id":19578,"rating":0,"product":9436,"disease":2479},{"id":19576,"rating":0,"product":9436,"disease":2480},{"id":19579,"rating":0,"product":9436,"disease":2481},{"id":19581,"rating":0,"product":9445,"disease":2478},{"id":19580,"rating":0,"product":9445,"disease":2480},{"id":19582,"rating":0,"product":9445,"disease":2481},{"id":19584,"rating":0,"product":9445,"disease":2483},{"id":19586,"rating":0,"product":9445,"disease":5235},{"id":19587,"rating":0,"product":9445,"disease":5236},{"id":19588,"rating":0,"product":9446,"disease":5237},{"id":19589,"rating":0,"product":9446,"disease":5238},{"id":19590,"rating":0,"product":9446,"disease":5239},{"id":19601,"rating":0,"product":9457,"disease":5221},{"id":19603,"rating":0,"product":9457,"disease":5242},{"id":19607,"rating":0,"product":9458,"disease":2471},{"id":19608,"rating":0,"product":9458,"disease":2472},{"id":19610,"rating":0,"product":9458,"disease":2486},{"id":19606,"rating":0,"product":9458,"disease":5221},{"id":19604,"rating":0,"product":9458,"disease":5237},{"id":19605,"rating":0,"product":9458,"disease":5242},{"id":19609,"rating":0,"product":9458,"disease":5243},{"id":19611,"rating":0,"product":9458,"disease":5244},{"id":19613,"rating":0,"product":9460,"disease":5210},{"id":19614,"rating":0,"product":9460,"disease":5211},{"id":19612,"rating":0,"product":9460,"disease":5225},{"id":19943,"rating":0,"product":9632,"disease":5221},{"id":19942,"rating":0,"product":9632,"disease":5242},{"id":19944,"rating":0,"product":9632,"disease":5243},{"id":19945,"rating":0,"product":9632,"disease":5273},{"id":19949,"rating":0,"product":9638,"disease":2476},{"id":19950,"rating":0,"product":9638,"disease":5210},{"id":19952,"rating":0,"product":9638,"disease":5212},{"id":19946,"rating":0,"product":9638,"disease":5224},{"id":19947,"rating":0,"product":9638,"disease":5225},{"id":19951,"rating":0,"product":9638,"disease":5274},{"id":19953,"rating":0,"product":9638,"disease":5275},{"id":19954,"rating":0,"product":9638,"disease":5276},{"id":19955,"rating":0,"product":9640,"disease":5224},{"id":19956,"rating":0,"product":9641,"disease":2472},{"id":19957,"rating":0,"product":9643,"disease":2478},{"id":19959,"rating":0,"product":9643,"disease":2479},{"id":19958,"rating":0,"product":9643,"disease":2480},{"id":19962,"rating":0,"product":9643,"disease":2483},{"id":19961,"rating":0,"product":9643,"disease":2484},{"id":19963,"rating":0,"product":9644,"disease":2478},{"id":19969,"rating":0,"product":9644,"disease":2480},{"id":19966,"rating":0,"product":9644,"disease":2481},{"id":19967,"rating":0,"product":9644,"disease":2483},{"id":19964,"rating":0,"product":9644,"disease":5235},{"id":19965,"rating":0,"product":9644,"disease":5236},{"id":19970,"rating":0,"product":9646,"disease":5210},{"id":19977,"rating":0,"product":9646,"disease":5277},{"id":19982,"rating":0,"product":9652,"disease":5224},{"id":19983,"rating":0,"product":9653,"disease":2471},{"id":19984,"rating":0,"product":9653,"disease":2486},{"id":19992,"rating":0,"product":9654,"disease":2471},{"id":19993,"rating":0,"product":9654,"disease":2472},{"id":19985,"rating":0,"product":9654,"disease":2478},{"id":19987,"rating":0,"product":9654,"disease":2479},{"id":19986,"rating":0,"product":9654,"disease":2480},{"id":19989,"rating":0,"product":9654,"disease":2481},{"id":19991,"rating":0,"product":9654,"disease":2483},{"id":19990,"rating":0,"product":9654,"disease":2484},{"id":19995,"rating":0,"product":9655,"disease":2471},{"id":19994,"rating":0,"product":9655,"disease":2472},{"id":19997,"rating":0,"product":9655,"disease":2473},{"id":19996,"rating":0,"product":9655,"disease":2476},{"id":19998,"rating":0,"product":9655,"disease":5279},{"id":19999,"rating":0,"product":9655,"disease":5280},{"id":20000,"rating":0,"product":9656,"disease":2472},{"id":20001,"rating":0,"product":9656,"disease":5243},{"id":20002,"rating":0,"product":9657,"disease":2471},{"id":20005,"rating":0,"product":9657,"disease":2472},{"id":20006,"rating":0,"product":9657,"disease":2485},{"id":20003,"rating":0,"product":9657,"disease":2486},{"id":20004,"rating":0,"product":9657,"disease":5244},{"id":20007,"rating":0,"product":9662,"disease":2478},{"id":20009,"rating":0,"product":9662,"disease":2479},{"id":20008,"rating":0,"product":9662,"disease":2480},{"id":20010,"rating":0,"product":9662,"disease":2483},{"id":20011,"rating":0,"product":9662,"disease":2484},{"id":20312,"rating":0,"product":9882,"disease":2481},{"id":20313,"rating":0,"product":9882,"disease":5305},{"id":20314,"rating":0,"product":9882,"disease":5306},{"id":20315,"rating":0,"product":9882,"disease":5307},{"id":20339,"rating":0,"product":9910,"disease":2481},{"id":20337,"rating":0,"product":9910,"disease":5305},{"id":20338,"rating":0,"product":9910,"disease":5306},{"id":20340,"rating":0,"product":9910,"disease":5307},{"id":28937,"rating":0,"product":17188,"disease":2478},{"id":28939,"rating":0,"product":17188,"disease":2479},{"id":28938,"rating":0,"product":17188,"disease":2480},{"id":28940,"rating":0,"product":17188,"disease":2481},{"id":28941,"rating":0,"product":17194,"disease":2478},{"id":28942,"rating":0,"product":17194,"disease":2479},{"id":28943,"rating":0,"product":17194,"disease":2480},{"id":28944,"rating":0,"product":17194,"disease":2481},{"id":28945,"rating":0,"product":17194,"disease":2483},{"id":28947,"rating":0,"product":17198,"disease":2478},{"id":28948,"rating":0,"product":17198,"disease":2479},{"id":28949,"rating":0,"product":17198,"disease":2480},{"id":28950,"rating":0,"product":17198,"disease":2481},{"id":28951,"rating":0,"product":17198,"disease":2482},{"id":28952,"rating":0,"product":17198,"disease":2483},{"id":28954,"rating":0,"product":17198,"disease":5279},{"id":28955,"rating":0,"product":17198,"disease":5280},{"id":28959,"rating":0,"product":17205,"disease":2478},{"id":28961,"rating":0,"product":17205,"disease":2479},{"id":28964,"rating":0,"product":17205,"disease":2480},{"id":28958,"rating":0,"product":17205,"disease":2481},{"id":28965,"rating":0,"product":17205,"disease":2482},{"id":28960,"rating":0,"product":17205,"disease":2483},{"id":28962,"rating":0,"product":17205,"disease":5235},{"id":28963,"rating":0,"product":17205,"disease":5236},{"id":28966,"rating":0,"product":17205,"disease":5307},{"id":28968,"rating":0,"product":17208,"disease":2478},{"id":28971,"rating":0,"product":17208,"disease":2479},{"id":28972,"rating":0,"product":17208,"disease":2480},{"id":28970,"rating":0,"product":17208,"disease":2483},{"id":28982,"rating":0,"product":17213,"disease":2478},{"id":28985,"rating":0,"product":17213,"disease":2480},{"id":28983,"rating":0,"product":17213,"disease":2481},{"id":28984,"rating":0,"product":17213,"disease":5235},{"id":29445,"rating":0,"product":17696,"disease":2471},{"id":29446,"rating":0,"product":17696,"disease":2472},{"id":29447,"rating":0,"product":17696,"disease":2473},{"id":29453,"rating":0,"product":17696,"disease":2476},{"id":29454,"rating":0,"product":17696,"disease":2485},{"id":29456,"rating":0,"product":17704,"disease":2471},{"id":29457,"rating":0,"product":17704,"disease":2472},{"id":29458,"rating":0,"product":17704,"disease":2476},{"id":29455,"rating":0,"product":17704,"disease":2485},{"id":29459,"rating":0,"product":17704,"disease":5244},{"id":29481,"rating":0,"product":17712,"disease":5212},{"id":29482,"rating":0,"product":17712,"disease":5221},{"id":29483,"rating":0,"product":17712,"disease":5222},{"id":29480,"rating":0,"product":17712,"disease":5224},{"id":29496,"rating":0,"product":17712,"disease":5274},{"id":29484,"rating":0,"product":17712,"disease":5275},{"id":29498,"rating":0,"product":17715,"disease":2476},{"id":29500,"rating":0,"product":17715,"disease":5210},{"id":29499,"rating":0,"product":17715,"disease":5211},{"id":29501,"rating":0,"product":17715,"disease":5224},{"id":29497,"rating":0,"product":17715,"disease":5225},{"id":29508,"rating":0,"product":17716,"disease":2476},{"id":29502,"rating":0,"product":17716,"disease":5224},{"id":29506,"rating":0,"product":17716,"disease":5229},{"id":29507,"rating":0,"product":17716,"disease":5230},{"id":29503,"rating":0,"product":17716,"disease":5237},{"id":29504,"rating":0,"product":17716,"disease":5238},{"id":29509,"rating":0,"product":17717,"disease":2472},{"id":30123,"rating":0,"product":18036,"disease":5221},{"id":30122,"rating":0,"product":18036,"disease":5222},{"id":30124,"rating":0,"product":18036,"disease":5224},{"id":30125,"rating":0,"product":18036,"disease":5273},{"id":30160,"rating":0,"product":18043,"disease":5224},{"id":30172,"rating":0,"product":18049,"disease":5237},{"id":30171,"rating":0,"product":18049,"disease":5242},{"id":30241,"rating":0,"product":18065,"disease":5210},{"id":30238,"rating":0,"product":18065,"disease":5211},{"id":30244,"rating":0,"product":18065,"disease":5221},{"id":30243,"rating":0,"product":18065,"disease":5222},{"id":30240,"rating":0,"product":18065,"disease":5224},{"id":30237,"rating":0,"product":18065,"disease":5225},{"id":30236,"rating":0,"product":18065,"disease":5226},{"id":30245,"rating":0,"product":18065,"disease":5229},{"id":30242,"rating":0,"product":18065,"disease":5230},{"id":30304,"rating":0,"product":18076,"disease":5237},{"id":54953,"rating":0,"product":18080,"disease":2472},{"id":54951,"rating":0,"product":18080,"disease":2476},{"id":54955,"rating":0,"product":18080,"disease":5221},{"id":54954,"rating":0,"product":18080,"disease":5222},{"id":54952,"rating":0,"product":18080,"disease":5242},{"id":30311,"rating":0,"product":18084,"disease":5221},{"id":30310,"rating":0,"product":18084,"disease":5242},{"id":54479,"rating":0,"product":67640,"disease":5280},{"id":54478,"rating":0,"product":67640,"disease":9161},{"id":54486,"rating":0,"product":67642,"disease":2471},{"id":54480,"rating":0,"product":67642,"disease":2476},{"id":54482,"rating":0,"product":67642,"disease":2478},{"id":54487,"rating":0,"product":67642,"disease":2479},{"id":54488,"rating":0,"product":67642,"disease":2480},{"id":54483,"rating":0,"product":67642,"disease":2481},{"id":54484,"rating":0,"product":67642,"disease":2482},{"id":54485,"rating":0,"product":67642,"disease":2483},{"id":54481,"rating":0,"product":67642,"disease":2484},{"id":53510,"rating":0,"product":67797,"disease":5225},{"id":53509,"rating":0,"product":67798,"disease":5210},{"id":53508,"rating":0,"product":67798,"disease":5224},{"id":53507,"rating":0,"product":67798,"disease":5225},{"id":53511,"rating":0,"product":67812,"disease":5224},{"id":53515,"rating":0,"product":67826,"disease":5210},{"id":53513,"rating":0,"product":67826,"disease":5225},{"id":53512,"rating":0,"product":67826,"disease":5277},{"id":53514,"rating":0,"product":67826,"disease":8869},{"id":53516,"rating":0,"product":67837,"disease":5225},{"id":53518,"rating":0,"product":67867,"disease":5224},{"id":53517,"rating":0,"product":67867,"disease":5225},{"id":54028,"rating":0,"product":67914,"disease":2481},{"id":54033,"rating":0,"product":67916,"disease":2473},{"id":54030,"rating":0,"product":67916,"disease":2478},{"id":54034,"rating":0,"product":67916,"disease":5221},{"id":54032,"rating":0,"product":67916,"disease":5237},{"id":54031,"rating":0,"product":67916,"disease":5242},{"id":54029,"rating":0,"product":67916,"disease":5279},{"id":54037,"rating":0,"product":67919,"disease":5221},{"id":54036,"rating":0,"product":67919,"disease":5237},{"id":54035,"rating":0,"product":67919,"disease":5242},{"id":54038,"rating":0,"product":67922,"disease":5225},{"id":54039,"rating":0,"product":67942,"disease":2481},{"id":54040,"rating":0,"product":67942,"disease":5305},{"id":54042,"rating":0,"product":67942,"disease":5306},{"id":54041,"rating":0,"product":67942,"disease":5307},{"id":53992,"rating":0,"product":68074,"disease":2478},{"id":53995,"rating":0,"product":68074,"disease":2479},{"id":53996,"rating":0,"product":68074,"disease":2480},{"id":53993,"rating":0,"product":68074,"disease":2481},{"id":53994,"rating":0,"product":68074,"disease":2482},{"id":53998,"rating":0,"product":68075,"disease":5221},{"id":53999,"rating":0,"product":68075,"disease":5273},{"id":53997,"rating":0,"product":68075,"disease":9095},{"id":54001,"rating":0,"product":68076,"disease":2478},{"id":54008,"rating":0,"product":68076,"disease":2480},{"id":54002,"rating":0,"product":68076,"disease":2481},{"id":54003,"rating":0,"product":68076,"disease":2482},{"id":54006,"rating":0,"product":68076,"disease":5210},{"id":54005,"rating":0,"product":68076,"disease":5224},{"id":54004,"rating":0,"product":68076,"disease":5225},{"id":54000,"rating":0,"product":68076,"disease":5226},{"id":54007,"rating":0,"product":68076,"disease":5235},{"id":54014,"rating":0,"product":68077,"disease":2471},{"id":54015,"rating":0,"product":68077,"disease":2472},{"id":54009,"rating":0,"product":68077,"disease":2478},{"id":54017,"rating":0,"product":68077,"disease":2479},{"id":54011,"rating":0,"product":68077,"disease":2481},{"id":54012,"rating":0,"product":68077,"disease":2482},{"id":54016,"rating":0,"product":68077,"disease":2485},{"id":54013,"rating":0,"product":68077,"disease":2486},{"id":54010,"rating":0,"product":68077,"disease":5244},{"id":54019,"rating":0,"product":68078,"disease":5224},{"id":54018,"rating":0,"product":68078,"disease":5225},{"id":54020,"rating":0,"product":68079,"disease":2476},{"id":54022,"rating":0,"product":68079,"disease":5224},{"id":54021,"rating":0,"product":68079,"disease":5225},{"id":54024,"rating":0,"product":68080,"disease":5210},{"id":54023,"rating":0,"product":68080,"disease":5225},{"id":54025,"rating":0,"product":68081,"disease":2478},{"id":54027,"rating":0,"product":68081,"disease":5237},{"id":54026,"rating":0,"product":68081,"disease":5242},{"id":70227,"rating":0,"product":68093,"disease":2481},{"id":70228,"rating":0,"product":68093,"disease":5305},{"id":70229,"rating":0,"product":68093,"disease":8943},{"id":54055,"rating":0,"product":68298,"disease":2481},{"id":54056,"rating":0,"product":68298,"disease":5305},{"id":54058,"rating":0,"product":68298,"disease":5306},{"id":54057,"rating":0,"product":68298,"disease":5307},{"id":54065,"rating":0,"product":68304,"disease":2481},{"id":54066,"rating":0,"product":68304,"disease":5305},{"id":54068,"rating":0,"product":68304,"disease":5306},{"id":54067,"rating":0,"product":68304,"disease":5307},{"id":54071,"rating":0,"product":68307,"disease":2481},{"id":54072,"rating":0,"product":68307,"disease":5305},{"id":54074,"rating":0,"product":68307,"disease":5306},{"id":54073,"rating":0,"product":68307,"disease":5307},{"id":54269,"rating":0,"product":68366,"disease":5212},{"id":54273,"rating":0,"product":68366,"disease":5221},{"id":54271,"rating":0,"product":68366,"disease":5224},{"id":54270,"rating":0,"product":68366,"disease":5225},{"id":54268,"rating":0,"product":68366,"disease":5274},{"id":54272,"rating":0,"product":68366,"disease":5275},{"id":54274,"rating":0,"product":68366,"disease":9512},{"id":54287,"rating":0,"product":68368,"disease":2472},{"id":54279,"rating":0,"product":68368,"disease":2478},{"id":54290,"rating":0,"product":68368,"disease":2479},{"id":54291,"rating":0,"product":68368,"disease":2480},{"id":54283,"rating":0,"product":68368,"disease":2481},{"id":54284,"rating":0,"product":68368,"disease":2482},{"id":54286,"rating":0,"product":68368,"disease":2483},{"id":54278,"rating":0,"product":68368,"disease":2484},{"id":54288,"rating":0,"product":68368,"disease":2485},{"id":54285,"rating":0,"product":68368,"disease":2486},{"id":54289,"rating":0,"product":68368,"disease":5221},{"id":54282,"rating":0,"product":68368,"disease":5237},{"id":54280,"rating":0,"product":68368,"disease":5242},{"id":54281,"rating":0,"product":68368,"disease":5244},{"id":54298,"rating":0,"product":68370,"disease":2471},{"id":54299,"rating":0,"product":68370,"disease":2472},{"id":54293,"rating":0,"product":68370,"disease":2478},{"id":54301,"rating":0,"product":68370,"disease":2479},{"id":54302,"rating":0,"product":68370,"disease":2480},{"id":54294,"rating":0,"product":68370,"disease":2481},{"id":54295,"rating":0,"product":68370,"disease":2482},{"id":54297,"rating":0,"product":68370,"disease":2483},{"id":54292,"rating":0,"product":68370,"disease":2484},{"id":54300,"rating":0,"product":68370,"disease":2485},{"id":54296,"rating":0,"product":68370,"disease":2486},{"id":54303,"rating":0,"product":68370,"disease":5244},{"id":54306,"rating":0,"product":68372,"disease":5225},{"id":54376,"rating":0,"product":68374,"disease":2478},{"id":54379,"rating":0,"product":68374,"disease":2480},{"id":54377,"rating":0,"product":68374,"disease":2481},{"id":54378,"rating":0,"product":68374,"disease":5235},{"id":54444,"rating":0,"product":68436,"disease":2471},{"id":54445,"rating":0,"product":68436,"disease":2472},{"id":54441,"rating":0,"product":68436,"disease":2476},{"id":54435,"rating":3,"product":68436,"disease":2478},{"id":54446,"rating":3,"product":68436,"disease":2479},{"id":54440,"rating":3,"product":68436,"disease":2480},{"id":54436,"rating":3,"product":68436,"disease":2481},{"id":54437,"rating":3,"product":68436,"disease":2482},{"id":54438,"rating":0,"product":68436,"disease":2483},{"id":54442,"rating":0,"product":68436,"disease":2484},{"id":54443,"rating":0,"product":68436,"disease":2486},{"id":54439,"rating":3,"product":68436,"disease":5235},{"id":54418,"rating":0,"product":68437,"disease":2472},{"id":54417,"rating":0,"product":68437,"disease":5243},{"id":41898,"rating":0,"product":68534,"disease":2476},{"id":41900,"rating":0,"product":68534,"disease":5211},{"id":41899,"rating":0,"product":68534,"disease":5225},{"id":41902,"rating":0,"product":68535,"disease":2478},{"id":41906,"rating":0,"product":68535,"disease":2479},{"id":41905,"rating":0,"product":68535,"disease":2481},{"id":41907,"rating":0,"product":68535,"disease":2482},{"id":41901,"rating":0,"product":68535,"disease":2484},{"id":41904,"rating":0,"product":68535,"disease":5237},{"id":41903,"rating":0,"product":68535,"disease":5242},{"id":46271,"rating":0,"product":68535,"disease":9129},{"id":41910,"rating":0,"product":68536,"disease":2471},{"id":41911,"rating":0,"product":68536,"disease":2472},{"id":41909,"rating":0,"product":68536,"disease":2473},{"id":41908,"rating":0,"product":68536,"disease":2476},{"id":42355,"rating":0,"product":68558,"disease":2471},{"id":42356,"rating":0,"product":68558,"disease":2472},{"id":43884,"rating":0,"product":68558,"disease":2473},{"id":46245,"rating":0,"product":68558,"disease":2476},{"id":42352,"rating":0,"product":68558,"disease":2478},{"id":42358,"rating":0,"product":68558,"disease":2479},{"id":42359,"rating":0,"product":68558,"disease":2480},{"id":42353,"rating":0,"product":68558,"disease":2481},{"id":42360,"rating":0,"product":68558,"disease":2482},{"id":46246,"rating":0,"product":68558,"disease":2484},{"id":42357,"rating":0,"product":68558,"disease":2485},{"id":43883,"rating":0,"product":68558,"disease":8923},{"id":43882,"rating":0,"product":68558,"disease":8924},{"id":46243,"rating":3,"product":68558,"disease":9125},{"id":46244,"rating":3,"product":68558,"disease":9126},{"id":42344,"rating":0,"product":68559,"disease":5210},{"id":42345,"rating":0,"product":68559,"disease":5221},{"id":43844,"rating":0,"product":68559,"disease":5277},{"id":43846,"rating":0,"product":68559,"disease":8869},{"id":42346,"rating":0,"product":68559,"disease":8870},{"id":43843,"rating":0,"product":68559,"disease":8921},{"id":43845,"rating":0,"product":68559,"disease":8922},{"id":42780,"rating":0,"product":68562,"disease":2481},{"id":42781,"rating":0,"product":68562,"disease":5305},{"id":42783,"rating":0,"product":68562,"disease":5306},{"id":42782,"rating":0,"product":68562,"disease":5307},{"id":42808,"rating":0,"product":68564,"disease":2471},{"id":42809,"rating":0,"product":68564,"disease":2472},{"id":42802,"rating":0,"product":68564,"disease":2476},{"id":42810,"rating":0,"product":68564,"disease":2485},{"id":42811,"rating":0,"product":68564,"disease":5221},{"id":42803,"rating":0,"product":68564,"disease":5226},{"id":42806,"rating":0,"product":68564,"disease":5237},{"id":42805,"rating":0,"product":68564,"disease":5242},{"id":42807,"rating":0,"product":68564,"disease":5243},{"id":42804,"rating":0,"product":68564,"disease":5244},{"id":42816,"rating":0,"product":68568,"disease":2481},{"id":42817,"rating":0,"product":68568,"disease":5305},{"id":42819,"rating":0,"product":68568,"disease":5306},{"id":42818,"rating":0,"product":68568,"disease":5307},{"id":42823,"rating":0,"product":68581,"disease":2471},{"id":42822,"rating":0,"product":68581,"disease":2476},{"id":42824,"rating":0,"product":68586,"disease":2481},{"id":42825,"rating":0,"product":68586,"disease":5305},{"id":42827,"rating":0,"product":68586,"disease":5306},{"id":42826,"rating":0,"product":68586,"disease":5307},{"id":46751,"rating":0,"product":68593,"disease":2471},{"id":46752,"rating":0,"product":68593,"disease":2472},{"id":46753,"rating":0,"product":68593,"disease":2485},{"id":46750,"rating":0,"product":68593,"disease":2486},{"id":46754,"rating":0,"product":68593,"disease":5221},{"id":46744,"rating":0,"product":68593,"disease":5226},{"id":46748,"rating":0,"product":68593,"disease":5237},{"id":46746,"rating":0,"product":68593,"disease":5242},{"id":46749,"rating":0,"product":68593,"disease":5243},{"id":46747,"rating":0,"product":68593,"disease":5244},{"id":46745,"rating":0,"product":68593,"disease":9161},{"id":42834,"rating":0,"product":68597,"disease":2472},{"id":42832,"rating":0,"product":68597,"disease":5210},{"id":42835,"rating":0,"product":68597,"disease":5221},{"id":42831,"rating":0,"product":68597,"disease":5224},{"id":42833,"rating":0,"product":68597,"disease":5232},{"id":42829,"rating":0,"product":68597,"disease":5237},{"id":42828,"rating":0,"product":68597,"disease":5242},{"id":64624,"rating":0,"product":68597,"disease":9161},{"id":42842,"rating":0,"product":68600,"disease":2472},{"id":42836,"rating":0,"product":68600,"disease":2476},{"id":42841,"rating":0,"product":68600,"disease":5210},{"id":42843,"rating":0,"product":68600,"disease":5221},{"id":42840,"rating":0,"product":68600,"disease":5224},{"id":42838,"rating":0,"product":68600,"disease":5237},{"id":42837,"rating":0,"product":68600,"disease":5242},{"id":42844,"rating":0,"product":68608,"disease":5224},{"id":42954,"rating":0,"product":68646,"disease":2471},{"id":42955,"rating":0,"product":68646,"disease":2472},{"id":42951,"rating":0,"product":68646,"disease":2473},{"id":42947,"rating":0,"product":68646,"disease":2476},{"id":42949,"rating":0,"product":68646,"disease":2478},{"id":42957,"rating":0,"product":68646,"disease":2479},{"id":42958,"rating":0,"product":68646,"disease":2480},{"id":42952,"rating":0,"product":68646,"disease":2481},{"id":42953,"rating":0,"product":68646,"disease":2483},{"id":44632,"rating":0,"product":68646,"disease":2484},{"id":42956,"rating":0,"product":68646,"disease":2485},{"id":46248,"rating":0,"product":68646,"disease":2486},{"id":42950,"rating":0,"product":68646,"disease":5244},{"id":46247,"rating":0,"product":68646,"disease":9128},{"id":42946,"rating":0,"product":68648,"disease":5224},{"id":42945,"rating":0,"product":68648,"disease":5225},{"id":55528,"rating":0,"product":68695,"disease":2471},{"id":55529,"rating":0,"product":68695,"disease":2472},{"id":55524,"rating":0,"product":68695,"disease":2473},{"id":55520,"rating":0,"product":68695,"disease":2476},{"id":55522,"rating":0,"product":68695,"disease":2478},{"id":55531,"rating":0,"product":68695,"disease":2479},{"id":55532,"rating":0,"product":68695,"disease":2480},{"id":55525,"rating":0,"product":68695,"disease":2481},{"id":55526,"rating":0,"product":68695,"disease":2482},{"id":55527,"rating":0,"product":68695,"disease":2483},{"id":55521,"rating":0,"product":68695,"disease":2484},{"id":55530,"rating":0,"product":68695,"disease":2485},{"id":55523,"rating":0,"product":68695,"disease":5244},{"id":55639,"rating":0,"product":68701,"disease":2478},{"id":55643,"rating":0,"product":68701,"disease":2479},{"id":55644,"rating":0,"product":68701,"disease":2480},{"id":55640,"rating":0,"product":68701,"disease":2481},{"id":55641,"rating":0,"product":68701,"disease":2482},{"id":55642,"rating":0,"product":68701,"disease":2483},{"id":55638,"rating":0,"product":68701,"disease":2484},{"id":55662,"rating":0,"product":68703,"disease":2481},{"id":55877,"rating":0,"product":68781,"disease":2471},{"id":55878,"rating":0,"product":68781,"disease":2472},{"id":55876,"rating":0,"product":68781,"disease":2473},{"id":55875,"rating":0,"product":68781,"disease":2476},{"id":55879,"rating":0,"product":68781,"disease":9547},{"id":55895,"rating":0,"product":68783,"disease":5212},{"id":55897,"rating":0,"product":68783,"disease":5224},{"id":55896,"rating":0,"product":68783,"disease":5225},{"id":55894,"rating":0,"product":68783,"disease":5226},{"id":55664,"rating":0,"product":68785,"disease":5221},{"id":55663,"rating":0,"product":68785,"disease":5242},{"id":55645,"rating":0,"product":68786,"disease":5224},{"id":55874,"rating":0,"product":68787,"disease":5237},{"id":55884,"rating":0,"product":68932,"disease":5210},{"id":55885,"rating":0,"product":68932,"disease":5213},{"id":55661,"rating":0,"product":68932,"disease":5224},{"id":55882,"rating":0,"product":68932,"disease":5225},{"id":55880,"rating":0,"product":68932,"disease":5226},{"id":55886,"rating":0,"product":68932,"disease":5230},{"id":55887,"rating":0,"product":68932,"disease":5232},{"id":55881,"rating":0,"product":68932,"disease":8921},{"id":55883,"rating":0,"product":68932,"disease":8922},{"id":54945,"rating":0,"product":69013,"disease":2478},{"id":54946,"rating":0,"product":69013,"disease":2481},{"id":54947,"rating":0,"product":69013,"disease":2482},{"id":54949,"rating":0,"product":69013,"disease":5236},{"id":54948,"rating":0,"product":69013,"disease":5305},{"id":54950,"rating":0,"product":69013,"disease":5306},{"id":54944,"rating":0,"product":69013,"disease":9161},{"id":54979,"rating":0,"product":69023,"disease":2481},{"id":54978,"rating":0,"product":69023,"disease":5277},{"id":54980,"rating":0,"product":69023,"disease":5305},{"id":54982,"rating":0,"product":69023,"disease":5306},{"id":54981,"rating":0,"product":69023,"disease":5307},{"id":54993,"rating":0,"product":69039,"disease":2472},{"id":54991,"rating":0,"product":69039,"disease":5223},{"id":54990,"rating":0,"product":69039,"disease":5243},{"id":54992,"rating":0,"product":69039,"disease":5273},{"id":55972,"rating":0,"product":69172,"disease":5212},{"id":55975,"rating":0,"product":69172,"disease":5221},{"id":55974,"rating":0,"product":69172,"disease":5224},{"id":55973,"rating":0,"product":69172,"disease":5225},{"id":42280,"rating":0,"product":69182,"disease":2472},{"id":42278,"rating":0,"product":69182,"disease":5210},{"id":42275,"rating":0,"product":69182,"disease":5211},{"id":42281,"rating":0,"product":69182,"disease":5221},{"id":42277,"rating":0,"product":69182,"disease":5224},{"id":42274,"rating":0,"product":69182,"disease":5225},{"id":42279,"rating":0,"product":69182,"disease":5273},{"id":42273,"rating":0,"product":69182,"disease":5277},{"id":42283,"rating":0,"product":69182,"disease":8868},{"id":42284,"rating":0,"product":69182,"disease":8869},{"id":42285,"rating":0,"product":69182,"disease":8870},{"id":55976,"rating":0,"product":69756,"disease":5225},{"id":45608,"rating":0,"product":70887,"disease":2476},{"id":45610,"rating":0,"product":70887,"disease":2481},{"id":45613,"rating":0,"product":70887,"disease":5211},{"id":45616,"rating":0,"product":70887,"disease":5213},{"id":45620,"rating":0,"product":70887,"disease":5221},{"id":45615,"rating":0,"product":70887,"disease":5224},{"id":45612,"rating":0,"product":70887,"disease":5225},{"id":45622,"rating":0,"product":70887,"disease":5229},{"id":45618,"rating":0,"product":70887,"disease":5230},{"id":45617,"rating":0,"product":70887,"disease":5243},{"id":45619,"rating":0,"product":70887,"disease":5273},{"id":45624,"rating":0,"product":70887,"disease":5274},{"id":45611,"rating":0,"product":70887,"disease":5305},{"id":45609,"rating":0,"product":70887,"disease":8868},{"id":45621,"rating":0,"product":70887,"disease":8870},{"id":45614,"rating":0,"product":70887,"disease":8922},{"id":45623,"rating":0,"product":70887,"disease":9093},{"id":45630,"rating":0,"product":70887,"disease":9094},{"id":45631,"rating":0,"product":70887,"disease":9095},{"id":45632,"rating":0,"product":70887,"disease":9096},{"id":45651,"rating":0,"product":70887,"disease":9097},{"id":45652,"rating":0,"product":70887,"disease":9098},{"id":45653,"rating":0,"product":70887,"disease":9099},{"id":45654,"rating":0,"product":70888,"disease":2476},{"id":45660,"rating":0,"product":70888,"disease":2481},{"id":45663,"rating":0,"product":70888,"disease":5211},{"id":45673,"rating":0,"product":70888,"disease":5221},{"id":45672,"rating":0,"product":70888,"disease":5222},{"id":45666,"rating":0,"product":70888,"disease":5224},{"id":45662,"rating":0,"product":70888,"disease":5225},{"id":45675,"rating":0,"product":70888,"disease":5229},{"id":45668,"rating":0,"product":70888,"disease":5230},{"id":45667,"rating":0,"product":70888,"disease":5243},{"id":45669,"rating":0,"product":70888,"disease":5273},{"id":45656,"rating":0,"product":70888,"disease":5274},{"id":45661,"rating":0,"product":70888,"disease":5305},{"id":45659,"rating":0,"product":70888,"disease":8868},{"id":45674,"rating":0,"product":70888,"disease":8870},{"id":45665,"rating":0,"product":70888,"disease":8922},{"id":45658,"rating":0,"product":70888,"disease":9093},{"id":45655,"rating":0,"product":70888,"disease":9094},{"id":45657,"rating":0,"product":70888,"disease":9095},{"id":45670,"rating":0,"product":70888,"disease":9097},{"id":45671,"rating":0,"product":70888,"disease":9099},{"id":45695,"rating":0,"product":70891,"disease":5237},{"id":64625,"rating":0,"product":70891,"disease":9161},{"id":54674,"rating":0,"product":70895,"disease":5237},{"id":54673,"rating":0,"product":70895,"disease":5242},{"id":64626,"rating":0,"product":70895,"disease":9161},{"id":54678,"rating":0,"product":70898,"disease":5221},{"id":54677,"rating":0,"product":70898,"disease":5237},{"id":54676,"rating":0,"product":70898,"disease":5242},{"id":54675,"rating":0,"product":70898,"disease":9161},{"id":54988,"rating":0,"product":73560,"disease":2471},{"id":54985,"rating":0,"product":73560,"disease":2473},{"id":54983,"rating":0,"product":73560,"disease":2476},{"id":54986,"rating":0,"product":73560,"disease":2481},{"id":54987,"rating":0,"product":73560,"disease":2482},{"id":54989,"rating":0,"product":73560,"disease":2485},{"id":54984,"rating":0,"product":73560,"disease":9128},{"id":53520,"rating":0,"product":75109,"disease":5237},{"id":53519,"rating":0,"product":75109,"disease":5242},{"id":53521,"rating":0,"product":75111,"disease":2472},{"id":53522,"rating":0,"product":75111,"disease":5222},{"id":53913,"rating":0,"product":75145,"disease":2471},{"id":53914,"rating":0,"product":75145,"disease":2472},{"id":53916,"rating":0,"product":75145,"disease":2479},{"id":53917,"rating":0,"product":75145,"disease":2480},{"id":53910,"rating":0,"product":75145,"disease":2481},{"id":53911,"rating":0,"product":75145,"disease":2482},{"id":53915,"rating":0,"product":75145,"disease":2485},{"id":53912,"rating":0,"product":75145,"disease":2486},{"id":53918,"rating":0,"product":75145,"disease":5229},{"id":53909,"rating":0,"product":75145,"disease":5237},{"id":53907,"rating":0,"product":75145,"disease":5242},{"id":53908,"rating":0,"product":75145,"disease":5244},{"id":53906,"rating":0,"product":75145,"disease":8924},{"id":53919,"rating":0,"product":75146,"disease":5221},{"id":53920,"rating":0,"product":75147,"disease":5221},{"id":53921,"rating":0,"product":75148,"disease":2478},{"id":53926,"rating":0,"product":75148,"disease":2480},{"id":53923,"rating":0,"product":75148,"disease":2481},{"id":53924,"rating":0,"product":75148,"disease":2482},{"id":53927,"rating":0,"product":75148,"disease":5229},{"id":53925,"rating":0,"product":75148,"disease":5305},{"id":53928,"rating":0,"product":75148,"disease":5306},{"id":53922,"rating":0,"product":75148,"disease":8923},{"id":53929,"rating":0,"product":75149,"disease":5237},{"id":53932,"rating":0,"product":75150,"disease":2479},{"id":53933,"rating":0,"product":75150,"disease":2480},{"id":53930,"rating":0,"product":75150,"disease":5235},{"id":53931,"rating":0,"product":75150,"disease":5236},{"id":53935,"rating":0,"product":75151,"disease":2478},{"id":53941,"rating":0,"product":75151,"disease":2479},{"id":53942,"rating":0,"product":75151,"disease":2480},{"id":53934,"rating":0,"product":75151,"disease":2484},{"id":53938,"rating":0,"product":75151,"disease":5230},{"id":53939,"rating":0,"product":75151,"disease":5235},{"id":53940,"rating":0,"product":75151,"disease":5236},{"id":53937,"rating":0,"product":75151,"disease":5280},{"id":53936,"rating":0,"product":75151,"disease":8923},{"id":53949,"rating":0,"product":75152,"disease":2471},{"id":53950,"rating":0,"product":75152,"disease":2472},{"id":53953,"rating":0,"product":75152,"disease":2480},{"id":53946,"rating":0,"product":75152,"disease":2481},{"id":53947,"rating":0,"product":75152,"disease":2482},{"id":53951,"rating":0,"product":75152,"disease":2485},{"id":53948,"rating":0,"product":75152,"disease":2486},{"id":53952,"rating":0,"product":75152,"disease":5236},{"id":53945,"rating":0,"product":75152,"disease":5244},{"id":53944,"rating":0,"product":75152,"disease":8923},{"id":53943,"rating":0,"product":75152,"disease":8924},{"id":53954,"rating":0,"product":75153,"disease":2478},{"id":53959,"rating":0,"product":75153,"disease":2480},{"id":53956,"rating":0,"product":75153,"disease":2481},{"id":53957,"rating":0,"product":75153,"disease":2482},{"id":53958,"rating":0,"product":75153,"disease":5305},{"id":53960,"rating":0,"product":75153,"disease":5306},{"id":53955,"rating":0,"product":75153,"disease":8923},{"id":53961,"rating":0,"product":75154,"disease":2478},{"id":53966,"rating":0,"product":75154,"disease":2480},{"id":53963,"rating":0,"product":75154,"disease":2481},{"id":53964,"rating":0,"product":75154,"disease":2482},{"id":53965,"rating":0,"product":75154,"disease":5305},{"id":53967,"rating":0,"product":75154,"disease":5306},{"id":53962,"rating":0,"product":75154,"disease":8923},{"id":53974,"rating":0,"product":75155,"disease":2471},{"id":53975,"rating":0,"product":75155,"disease":2472},{"id":53978,"rating":0,"product":75155,"disease":2480},{"id":53971,"rating":0,"product":75155,"disease":2481},{"id":53972,"rating":0,"product":75155,"disease":2482},{"id":53976,"rating":0,"product":75155,"disease":2485},{"id":53973,"rating":0,"product":75155,"disease":2486},{"id":53977,"rating":0,"product":75155,"disease":5236},{"id":53970,"rating":0,"product":75155,"disease":5244},{"id":53969,"rating":0,"product":75155,"disease":8923},{"id":53968,"rating":0,"product":75155,"disease":8924},{"id":53979,"rating":0,"product":75156,"disease":2478},{"id":53984,"rating":0,"product":75156,"disease":2480},{"id":53981,"rating":0,"product":75156,"disease":2481},{"id":53982,"rating":0,"product":75156,"disease":2482},{"id":53983,"rating":0,"product":75156,"disease":5305},{"id":53985,"rating":0,"product":75156,"disease":5306},{"id":53980,"rating":0,"product":75156,"disease":8923},{"id":53986,"rating":0,"product":75161,"disease":2481},{"id":53987,"rating":0,"product":75161,"disease":5305},{"id":54381,"rating":0,"product":75223,"disease":2478},{"id":54382,"rating":0,"product":75223,"disease":2480},{"id":54380,"rating":0,"product":75223,"disease":2484},{"id":54384,"rating":0,"product":75224,"disease":5212},{"id":54388,"rating":0,"product":75224,"disease":5221},{"id":54386,"rating":0,"product":75224,"disease":5224},{"id":54385,"rating":0,"product":75224,"disease":5225},{"id":54383,"rating":0,"product":75224,"disease":5226},{"id":54387,"rating":0,"product":75224,"disease":5243},{"id":54389,"rating":0,"product":75225,"disease":5237},{"id":70299,"rating":0,"product":75655,"disease":2471},{"id":70300,"rating":0,"product":75655,"disease":2472},{"id":70291,"rating":0,"product":75655,"disease":2473},{"id":70282,"rating":0,"product":75655,"disease":2476},{"id":70287,"rating":0,"product":75655,"disease":2478},{"id":70304,"rating":0,"product":75655,"disease":2479},{"id":70307,"rating":0,"product":75655,"disease":2480},{"id":70292,"rating":0,"product":75655,"disease":2481},{"id":70293,"rating":0,"product":75655,"disease":2482},{"id":70297,"rating":0,"product":75655,"disease":2483},{"id":70285,"rating":0,"product":75655,"disease":2484},{"id":70301,"rating":0,"product":75655,"disease":2485},{"id":70296,"rating":0,"product":75655,"disease":2486},{"id":70303,"rating":0,"product":75655,"disease":5221},{"id":70302,"rating":0,"product":75655,"disease":5222},{"id":70308,"rating":0,"product":75655,"disease":5229},{"id":70295,"rating":0,"product":75655,"disease":5230},{"id":70305,"rating":0,"product":75655,"disease":5235},{"id":70306,"rating":0,"product":75655,"disease":5236},{"id":70290,"rating":0,"product":75655,"disease":5237},{"id":70288,"rating":0,"product":75655,"disease":5242},{"id":70294,"rating":0,"product":75655,"disease":5243},{"id":70289,"rating":0,"product":75655,"disease":5244},{"id":70298,"rating":0,"product":75655,"disease":5273},{"id":70284,"rating":0,"product":75655,"disease":9094},{"id":70286,"rating":0,"product":75655,"disease":9095},{"id":70283,"rating":0,"product":75655,"disease":9128},{"id":70310,"rating":0,"product":75656,"disease":5224},{"id":70309,"rating":0,"product":75656,"disease":5225},{"id":70313,"rating":0,"product":75657,"disease":2471},{"id":70314,"rating":0,"product":75657,"disease":2472},{"id":70312,"rating":0,"product":75657,"disease":2486},{"id":70311,"rating":0,"product":75657,"disease":5226},{"id":70316,"rating":0,"product":75658,"disease":2471},{"id":70317,"rating":0,"product":75658,"disease":2472},{"id":70319,"rating":0,"product":75658,"disease":5221},{"id":70318,"rating":0,"product":75658,"disease":5222},{"id":70320,"rating":0,"product":75658,"disease":8870},{"id":70315,"rating":0,"product":75658,"disease":9095},{"id":70321,"rating":0,"product":75659,"disease":5279},{"id":70322,"rating":0,"product":75659,"disease":5280},{"id":70325,"rating":0,"product":75660,"disease":5221},{"id":70324,"rating":0,"product":75660,"disease":5237},{"id":70323,"rating":0,"product":75660,"disease":5242}]}